pygoruut/__init__.py
pygoruut/config.py
pygoruut/executable.py
pygoruut/goplatform.py
pygoruut/pygoruut.py
pygoruut/pygoruut_languages.py
pygoruut/releases.py
pygoruut-0.7.0.dist-info/licenses/LICENSE
pygoruut-0.7.0.dist-info/METADATA
pygoruut-0.7.0.dist-info/WHEEL
pygoruut-0.7.0.dist-info/top_level.txt
pygoruut-0.7.0.dist-info/RECORD
