Metadata-Version: 2.4
Name: pygoruut
Version: 0.7.0
Summary: Text-to-IPA converter and phonetic translator for Python, powered by the Goruut phonemization engine
Home-page: https://github.com/neurlang/pygoruut
Author: Neurlang Project
Author-email: Neurlang Project <77860779+neurlang@users.noreply.github.com>
License: MIT License
Project-URL: Homepage, https://github.com/neurlang/pygoruut
Keywords: goruut,phonemization,tts
Classifier: License :: OSI Approved :: MIT License
Classifier: Programming Language :: Python
Classifier: Programming Language :: Python :: 3
Requires-Python: >=3.6
License-File: LICENSE
Requires-Dist: requests
Dynamic: author
Dynamic: home-page
Dynamic: license-file
Dynamic: requires-python
